{
  "token": "8f594e6797e62459c34a40b408f10523",
  "updateTime": "2026/5/31 01:37:32",
  "vip": {
    "vip1": {
      "status": true,
      "expireTime": "2026/5/31 02:37:14",
      "expireTimestamp": 1780166234
    },
    "vip2": {
      "status": true,
      "expireTime": "2026/5/31 02:37:19",
      "expireTimestamp": 1780166239
    },
    "vip3": {
      "status": true,
      "expireTime": "2026/5/31 02:37:23",
      "expireTimestamp": 1780166243
    },
    "vip4": {
      "status": true,
      "expireTime": "2026/5/31 02:37:28",
      "expireTimestamp": 1780166248
    }
  }
}