{
  "token": "0f7a795ddc6a263104a8eeb98f3f8e6f",
  "updateTime": "2026/5/30 05:37:32",
  "vip": {
    "vip1": {
      "status": true,
      "expireTime": "2026/5/30 06:37:14",
      "expireTimestamp": 1780094234
    },
    "vip2": {
      "status": true,
      "expireTime": "2026/5/30 06:37:18",
      "expireTimestamp": 1780094238
    },
    "vip3": {
      "status": true,
      "expireTime": "2026/5/30 06:37:23",
      "expireTimestamp": 1780094243
    },
    "vip4": {
      "status": true,
      "expireTime": "2026/5/30 06:37:27",
      "expireTimestamp": 1780094247
    }
  }
}