{
  "token": "081ed3c1f9bca0b8e15c2b7a20317732",
  "updateTime": "2026/5/11 18:37:27",
  "vip": {
    "vip1": {
      "status": true,
      "expireTime": "2026/5/11 19:37:20",
      "expireTimestamp": 1778499440
    },
    "vip2": {
      "status": true,
      "expireTime": "2026/5/11 19:37:25",
      "expireTimestamp": 1778499445
    },
    "vip3": {
      "status": true,
      "expireTime": "2026/5/11 19:37:29",
      "expireTimestamp": 1778499449
    },
    "vip4": {
      "status": true,
      "expireTime": "2026/5/11 19:37:34",
      "expireTimestamp": 1778499454
    }
  }
}