{
  "token": "de9b15de0be83c93f8c29db978d5e7cf",
  "updateTime": "2026/6/2 10:37:32",
  "vip": {
    "vip1": {
      "status": true,
      "expireTime": "2026/6/2 11:37:15",
      "expireTimestamp": 1780371435
    },
    "vip2": {
      "status": true,
      "expireTime": "2026/6/2 11:37:20",
      "expireTimestamp": 1780371440
    },
    "vip3": {
      "status": true,
      "expireTime": "2026/6/2 11:37:24",
      "expireTimestamp": 1780371444
    },
    "vip4": {
      "status": true,
      "expireTime": "2026/6/2 11:37:29",
      "expireTimestamp": 1780371449
    }
  }
}