{
  "token": "edd84e9fcc802a3b357da4f21478a672",
  "updateTime": "2026/3/12 15:35:00",
  "vip": {
    "vip1": {
      "status": true,
      "expireTime": "2026/3/12 16:34:50",
      "expireTimestamp": 1773304490
    },
    "vip2": {
      "status": false,
      "expireTime": "未开通",
      "expireTimestamp": 0
    },
    "vip3": {
      "status": true,
      "expireTime": "2026/3/12 16:35:00",
      "expireTimestamp": 1773304500
    },
    "vip4": {
      "status": true,
      "expireTime": "2026/3/12 16:35:04",
      "expireTimestamp": 1773304504
    }
  }
}