{
  "token": "1e944003384ef4573cd6f126ebf627ef",
  "updateTime": "2026/5/30 00:37:32",
  "vip": {
    "vip1": {
      "status": true,
      "expireTime": "2026/5/30 01:37:14",
      "expireTimestamp": 1780076234
    },
    "vip2": {
      "status": true,
      "expireTime": "2026/5/30 01:37:18",
      "expireTimestamp": 1780076238
    },
    "vip3": {
      "status": true,
      "expireTime": "2026/5/30 01:37:23",
      "expireTimestamp": 1780076243
    },
    "vip4": {
      "status": true,
      "expireTime": "2026/5/30 01:37:27",
      "expireTimestamp": 1780076247
    }
  }
}