{
  "token": "0d64384fd1751f02e7fdc7c21c7067b6",
  "updateTime": "2026/4/3 22:53:03",
  "vip": {
    "vip1": {
      "status": true,
      "expireTime": "2026/4/3 23:53:02",
      "expireTimestamp": 1775231582
    },
    "vip2": {
      "status": true,
      "expireTime": "2026/4/3 23:53:06",
      "expireTimestamp": 1775231586
    },
    "vip3": {
      "status": true,
      "expireTime": "2026/4/3 23:53:10",
      "expireTimestamp": 1775231590
    },
    "vip4": {
      "status": true,
      "expireTime": "2026/4/3 23:53:15",
      "expireTimestamp": 1775231595
    }
  }
}