{
  "token": "4f0ed434b8d85dc8bef5fc7584c8de4a",
  "updateTime": "2026/5/16 17:37:26",
  "vip": {
    "vip1": {
      "status": true,
      "expireTime": "2026/5/16 18:37:22",
      "expireTimestamp": 1778927842
    },
    "vip2": {
      "status": true,
      "expireTime": "2026/5/16 18:37:27",
      "expireTimestamp": 1778927847
    },
    "vip3": {
      "status": true,
      "expireTime": "2026/5/16 18:37:31",
      "expireTimestamp": 1778927851
    },
    "vip4": {
      "status": true,
      "expireTime": "2026/5/16 18:37:36",
      "expireTimestamp": 1778927856
    }
  }
}