{
  "token": "d833323f48f7445b43b90052688dbeb1",
  "updateTime": "2026/3/28 04:10:58",
  "vip": {
    "vip1": {
      "status": true,
      "expireTime": "2026/3/28 05:10:54",
      "expireTimestamp": 1774645854
    },
    "vip2": {
      "status": true,
      "expireTime": "2026/3/28 05:10:59",
      "expireTimestamp": 1774645859
    },
    "vip3": {
      "status": true,
      "expireTime": "2026/3/28 05:11:03",
      "expireTimestamp": 1774645863
    },
    "vip4": {
      "status": true,
      "expireTime": "2026/3/28 05:11:08",
      "expireTimestamp": 1774645868
    }
  }
}