{
  "token": "93e5beb96beb4a41ec9cd8a51cd96e9b",
  "updateTime": "2026/3/26 06:10:58",
  "vip": {
    "vip1": {
      "status": true,
      "expireTime": "2026/3/26 07:10:54",
      "expireTimestamp": 1774480254
    },
    "vip2": {
      "status": true,
      "expireTime": "2026/3/26 07:10:58",
      "expireTimestamp": 1774480258
    },
    "vip3": {
      "status": true,
      "expireTime": "2026/3/26 07:11:02",
      "expireTimestamp": 1774480262
    },
    "vip4": {
      "status": true,
      "expireTime": "2026/3/26 07:11:07",
      "expireTimestamp": 1774480267
    }
  }
}