{
  "token": "e87d75f6763795d37efdc4154cc5d271",
  "updateTime": "2026/5/19 17:37:27",
  "vip": {
    "vip1": {
      "status": true,
      "expireTime": "2026/5/19 18:37:24",
      "expireTimestamp": 1779187044
    },
    "vip2": {
      "status": true,
      "expireTime": "2026/5/19 18:37:28",
      "expireTimestamp": 1779187048
    },
    "vip3": {
      "status": true,
      "expireTime": "2026/5/19 18:37:33",
      "expireTimestamp": 1779187053
    },
    "vip4": {
      "status": true,
      "expireTime": "2026/5/19 18:37:37",
      "expireTimestamp": 1779187057
    }
  }
}