{
  "token": "afc003cf135aef405e4f8f271261f330",
  "updateTime": "2026/3/30 15:53:02",
  "vip": {
    "vip1": {
      "status": true,
      "expireTime": "2026/3/30 16:53:00",
      "expireTimestamp": 1774860780
    },
    "vip2": {
      "status": true,
      "expireTime": "2026/3/30 16:53:04",
      "expireTimestamp": 1774860784
    },
    "vip3": {
      "status": true,
      "expireTime": "2026/3/30 16:53:09",
      "expireTimestamp": 1774860789
    },
    "vip4": {
      "status": true,
      "expireTime": "2026/3/30 16:53:13",
      "expireTimestamp": 1774860793
    }
  }
}