{
  "token": "d0ad3ca43b8bf4b85c9ded42252db14e",
  "updateTime": "2026/3/14 11:35:00",
  "vip": {
    "vip1": {
      "status": true,
      "expireTime": "2026/3/14 12:34:51",
      "expireTimestamp": 1773462891
    },
    "vip2": {
      "status": false,
      "expireTime": "未开通",
      "expireTimestamp": 0
    },
    "vip3": {
      "status": true,
      "expireTime": "2026/3/14 12:35:00",
      "expireTimestamp": 1773462900
    },
    "vip4": {
      "status": true,
      "expireTime": "2026/3/14 12:35:05",
      "expireTimestamp": 1773462905
    }
  }
}