{
  "token": "6955482800fb3d9af22a24ba2451a72a",
  "updateTime": "2026/3/11 01:35:00",
  "vip": {
    "vip1": {
      "status": true,
      "expireTime": "2026/3/11 02:34:49",
      "expireTimestamp": 1773167689
    },
    "vip2": {
      "status": false,
      "expireTime": "未开通",
      "expireTimestamp": 0
    },
    "vip3": {
      "status": true,
      "expireTime": "2026/3/11 02:34:59",
      "expireTimestamp": 1773167699
    },
    "vip4": {
      "status": true,
      "expireTime": "2026/3/11 02:35:03",
      "expireTimestamp": 1773167703
    }
  }
}